sqthon/__init__.py
sqthon/connection.py
sqthon/data_visualizer.py
sqthon/db_context.py
sqthon/exception.py
sqthon/llm.py
sqthon/main.py
sqthon/services.py
sqthon/util.py
sqthon-0.1.4.dist-info/LICENSE
sqthon-0.1.4.dist-info/METADATA
sqthon-0.1.4.dist-info/WHEEL
sqthon-0.1.4.dist-info/RECORD
