Metadata-Version: 2.1
Name: sqthon
Version: 0.1.4
Summary: A tool to connect, visualize and execute raw or LLM-generated SQL queries across multiple databases.
License: MIT
Author: HIMRAJ
Author-email: himraj.fordev@gmail.com
Requires-Python: >=3.12,<4.0
Classifier: License :: OSI Approved :: MIT License
Classifier: Programming Language :: Python :: 3
Classifier: Programming Language :: Python :: 3.12
Requires-Dist: cryptography (>=43.0.0,<44.0.0)
Requires-Dist: matplotlib (>=3.9.2,<4.0.0)
Requires-Dist: ollama (>=0.3.3,<0.4.0)
Requires-Dist: openai (>=1.57.3,<2.0.0)
Requires-Dist: pandas (>=2.2.2,<3.0.0)
Requires-Dist: psycopg2 (>=2.9.9,<3.0.0)
Requires-Dist: pymysql (>=1.1.1,<2.0.0)
Requires-Dist: python-dotenv (>=1.0.1,<2.0.0)
Requires-Dist: pywin32 (>=306,<307)
Requires-Dist: requests (>=2.32.3,<3.0.0)
Requires-Dist: rich (>=13.9.4,<14.0.0)
Requires-Dist: seaborn (>=0.13.2,<0.14.0)
Requires-Dist: sqlalchemy (>=2.0,<3.0)
Requires-Dist: tenacity (>=9.0.0,<10.0.0)
Requires-Dist: tiktoken (>=0.8.0,<0.9.0)
